autoload.py
autoloader.py
import_autoload-0.3.1.dist-info/LICENSE
import_autoload-0.3.1.dist-info/METADATA
import_autoload-0.3.1.dist-info/WHEEL
import_autoload-0.3.1.dist-info/top_level.txt
import_autoload-0.3.1.dist-info/RECORD
