Metadata-Version: 2.1
Name: import-autoload
Version: 0.3.1
Summary: This helper provides simplified loading of modules (files) from package (dir)
Author: JL Connor
License: GLWTPL
Keywords: autoload,autoloader,import,module
Classifier: Development Status :: 4 - Beta
Classifier: Intended Audience :: Developers
Classifier: License :: Freeware
Classifier: License :: OSI Approved :: BSD License
Classifier: Operating System :: OS Independent
Classifier: Programming Language :: Python :: 3
Classifier: Topic :: Software Development :: Libraries :: Python Modules
Requires-Python: >=3
License-File: LICENSE
